{   
    "_id": "",
    "nome": "Pamela",
    "data_nascimento": "1990-10-05",
    "email": "pamela.apolinario.borges@gmail.com",
    "endereco": "Av Manoel Marques de Jesus, 380 - Vila Xavier, Araraquara/SP"
}
// Ou
{   
    "_id": "1",
    "nome": "Julia",
    "data_nascimento": "2007-11-05",
    "email": "julia@gmail.com",
    "endereco": {
        "rua": "Nações Queridas",
        "numero": 123,
        "cidade": "Salto",
        "estado": "SP"
    }
}
// ou
{   
    "_id": "2",
    "nome": "Pedro",
    "data_nascimento": "2016-23-02",
    "email": "principe@gmail.com",
    "enderecos": [
        {
        "rua": "Av Brasil",
        "numero": 1223,
        "cidade": "Itu",
        "estado": "SP"
        },
        {
        "rua": "Av Do estado",
        "numero": 123,
        "cidade": "Araraquara",
        "estado": "SP"
        },
    ]
}

{
    "_id": "",
    "nome": "Aracaju",
    "descricao": "Descricao do destino"
}
